activity_tracker/__init__.py
activity_tracker/tracker.py
activity_tracker/backends/__init__.py
activity_tracker/backends/base.py
activity_tracker/backends/redis.py
activity_tracker-0.0.5.dist-info/LICENSE
activity_tracker-0.0.5.dist-info/METADATA
activity_tracker-0.0.5.dist-info/WHEEL
activity_tracker-0.0.5.dist-info/top_level.txt
activity_tracker-0.0.5.dist-info/RECORD
